schedule_llm_query/__init__.py
schedule_llm_query/main.py
schedule_llm_query/prompts.py
schedule_llm_query-2025.12.20185642.dist-info/METADATA
schedule_llm_query-2025.12.20185642.dist-info/WHEEL
schedule_llm_query-2025.12.20185642.dist-info/top_level.txt
schedule_llm_query-2025.12.20185642.dist-info/RECORD
