Metadata-Version: 2.4
Name: schedule-llm-query
Version: 2025.12.20185642
Summary: A new package that processes user queries about event schedules, such as FOSDEM 2026, and returns structured information like session times, locations, and descriptions. It uses an LLM to interpret na
Author-email: schedule-llm-query <hi@eugene.plus>
License: MIT
Project-URL: Homepage, https://github.com/chigwell/schedule-llm-query
Requires-Python: >=3.9
Requires-Dist: langchain-llm7>=0.0.0
Requires-Dist: llmatch-messages>=0.0.0
Requires-Dist: langchain-core>=0.3.0
